vdt.versionplugin.buildout-0.0.3-py2.7-nspkg.pth
vdt/versionplugin/buildout/__init__.py
vdt/versionplugin/buildout/package.py
vdt/versionplugin/buildout/shared.py
vdt/versionplugin/buildout/version.py
vdt/versionplugin/buildout/files/preremove
vdt/versionplugin/buildout/test/unit_test_shared.py
vdt/versionplugin/buildout/test/files/setup.py
vdt.versionplugin.buildout-0.0.3.dist-info/DESCRIPTION.rst
vdt.versionplugin.buildout-0.0.3.dist-info/METADATA
vdt.versionplugin.buildout-0.0.3.dist-info/metadata.json
vdt.versionplugin.buildout-0.0.3.dist-info/namespace_packages.txt
vdt.versionplugin.buildout-0.0.3.dist-info/RECORD
vdt.versionplugin.buildout-0.0.3.dist-info/top_level.txt
vdt.versionplugin.buildout-0.0.3.dist-info/WHEEL
vdt.versionplugin.buildout-0.0.3.dist-info/zip-safe
