Metadata-Version: 2.0
Name: vdt.versionplugin.buildout
Version: 0.0.3
Summary: Version Increment Plugin that builds with debianize
Home-page: UNKNOWN
Author: CSI
Author-email: csi@avira.com
License: UNKNOWN
Platform: UNKNOWN
Requires-Dist: setuptools
Requires-Dist: vdt.version
Requires-Dist: vdt.versionplugin.default
Requires-Dist: mock
